LICENSE
README.md
setup.cfg
setup.py
pi_MCP342x/__init__.py
pi_MCP342x/pi_MCP342x.py
pi_MCP342x.egg-info/PKG-INFO
pi_MCP342x.egg-info/SOURCES.txt
pi_MCP342x.egg-info/dependency_links.txt
pi_MCP342x.egg-info/requires.txt
pi_MCP342x.egg-info/top_level.txt