Metadata-Version: 2.1
Name: pi-MCP342x
Version: 0.1.1
Summary: Python module to use the MCP342x series of ADCs with the Raspberry Pi
Home-page: https://github.com/sergiocaponi/pi_MCP342x
Download-URL: https://github.com/sergiocaponi/pi_MCP342x/archive/refs/tags/v0.1.1.tar.gz
Author: Sergio Caponi
Author-email: contactme@sergiocaponi.com
License: MIT
Keywords: Raspberry Pi,ADC,MCP342x,MCP3422,MCP3423,MCP3424
Classifier: Development Status :: 3 - Alpha
Classifier: Intended Audience :: Developers
Classifier: Operating System :: POSIX :: Linux
Classifier: Topic :: Software Development :: Build Tools
Classifier: Topic :: System :: Hardware
Classifier: License :: OSI Approved :: MIT License
Classifier: Programming Language :: Python :: 3
License-File: LICENSE
